{
	"info": {
		"_postman_id": "20a04412-2747-466e-8063-1cd2d7990ef9",
		"name": "mmall",
		"schema": "https://schema.getpostman.com/json/collection/v2.1.0/collection.json"
	},
	"item": [
		{
			"name": "user",
			"item": [
				{
					"name": "login.do",
					"request": {
						"method": "POST",
						"header": [],
						"body": {
							"mode": "formdata",
							"formdata": [
								{
									"key": "username",
									"value": "admin",
									"type": "text"
								},
								{
									"key": "password",
									"value": "admin",
									"type": "text"
								}
							]
						},
						"url": {
							"raw": "http://localhost:8083/user/login.do",
							"protocol": "http",
							"host": [
								"localhost"
							],
							"port": "8083",
							"path": [
								"user",
								"login.do"
							]
						}
					},
					"response": []
				}
			]
		},
		{
			"name": "cart",
			"item": [
				{
					"name": "add.do",
					"request": {
						"method": "GET",
						"header": [],
						"body": {
							"mode": "raw",
							"raw": ""
						},
						"url": {
							"raw": "http://localhost:8083/cart/add.do?productId=26&count=101000000",
							"protocol": "http",
							"host": [
								"localhost"
							],
							"port": "8083",
							"path": [
								"cart",
								"add.do"
							],
							"query": [
								{
									"key": "productId",
									"value": "26"
								},
								{
									"key": "count",
									"value": "101000000"
								}
							]
						}
					},
					"response": []
				},
				{
					"name": "list.do",
					"request": {
						"method": "GET",
						"header": [],
						"body": {
							"mode": "raw",
							"raw": ""
						},
						"url": {
							"raw": "http://localhost:8083/cart/list.do",
							"protocol": "http",
							"host": [
								"localhost"
							],
							"port": "8083",
							"path": [
								"cart",
								"list.do"
							]
						}
					},
					"response": []
				},
				{
					"name": "update.do",
					"request": {
						"method": "GET",
						"header": [],
						"body": {
							"mode": "raw",
							"raw": ""
						},
						"url": {
							"raw": "http://localhost:8083/cart/update.do?productId=26&count=100",
							"protocol": "http",
							"host": [
								"localhost"
							],
							"port": "8083",
							"path": [
								"cart",
								"update.do"
							],
							"query": [
								{
									"key": "productId",
									"value": "26"
								},
								{
									"key": "count",
									"value": "100"
								}
							]
						}
					},
					"response": []
				},
				{
					"name": "delete_product",
					"request": {
						"method": "GET",
						"header": [],
						"body": {
							"mode": "raw",
							"raw": ""
						},
						"url": {
							"raw": "http://localhost:8083/cart/delete_product.do?productIds=26",
							"protocol": "http",
							"host": [
								"localhost"
							],
							"port": "8083",
							"path": [
								"cart",
								"delete_product.do"
							],
							"query": [
								{
									"key": "productIds",
									"value": "26"
								}
							]
						}
					},
					"response": []
				},
				{
					"name": "un_select",
					"request": {
						"method": "GET",
						"header": [],
						"body": {
							"mode": "raw",
							"raw": ""
						},
						"url": {
							"raw": "http://localhost:8083/cart/un_select.do?productId=26",
							"protocol": "http",
							"host": [
								"localhost"
							],
							"port": "8083",
							"path": [
								"cart",
								"un_select.do"
							],
							"query": [
								{
									"key": "productId",
									"value": "26"
								}
							]
						}
					},
					"response": []
				},
				{
					"name": "select",
					"request": {
						"method": "GET",
						"header": [],
						"body": {
							"mode": "raw",
							"raw": ""
						},
						"url": {
							"raw": "http://localhost:8083/cart/select.do?productId=26",
							"protocol": "http",
							"host": [
								"localhost"
							],
							"port": "8083",
							"path": [
								"cart",
								"select.do"
							],
							"query": [
								{
									"key": "productId",
									"value": "26"
								}
							]
						}
					},
					"response": []
				},
				{
					"name": "get_cart_product_count",
					"request": {
						"method": "GET",
						"header": [],
						"body": {
							"mode": "raw",
							"raw": ""
						},
						"url": {
							"raw": "http://localhost:8083/cart/get_cart_product_count.do",
							"protocol": "http",
							"host": [
								"localhost"
							],
							"port": "8083",
							"path": [
								"cart",
								"get_cart_product_count.do"
							]
						}
					},
					"response": []
				},
				{
					"name": "select_all",
					"request": {
						"method": "GET",
						"header": [],
						"body": {
							"mode": "raw",
							"raw": ""
						},
						"url": {
							"raw": "http://localhost:8083/cart/select_all.do",
							"protocol": "http",
							"host": [
								"localhost"
							],
							"port": "8083",
							"path": [
								"cart",
								"select_all.do"
							]
						}
					},
					"response": []
				},
				{
					"name": "un_select_all",
					"request": {
						"method": "GET",
						"header": [],
						"body": {
							"mode": "raw",
							"raw": ""
						},
						"url": {
							"raw": "http://localhost:8080/cart/un_select_all.do",
							"protocol": "http",
							"host": [
								"localhost"
							],
							"port": "8080",
							"path": [
								"cart",
								"un_select_all.do"
							]
						}
					},
					"response": []
				}
			]
		},
		{
			"name": "shipping",
			"item": [
				{
					"name": "add.do",
					"request": {
						"method": "GET",
						"header": [],
						"body": {
							"mode": "raw",
							"raw": ""
						},
						"url": {
							"raw": "http://localhost:8083/shipping/add.do?receiverName=爱迪生&receiverPhone=010&receiverMobile=18688888888&receiverProvince=北京&receiverCity=北京市&receiverAddress=中关村&receiverZip=100000",
							"protocol": "http",
							"host": [
								"localhost"
							],
							"port": "8083",
							"path": [
								"shipping",
								"add.do"
							],
							"query": [
								{
									"key": "userId",
									"value": "1",
									"disabled": true
								},
								{
									"key": "receiverName",
									"value": "爱迪生"
								},
								{
									"key": "receiverPhone",
									"value": "010"
								},
								{
									"key": "receiverMobile",
									"value": "18688888888"
								},
								{
									"key": "receiverProvince",
									"value": "北京"
								},
								{
									"key": "receiverCity",
									"value": "北京市"
								},
								{
									"key": "receiverAddress",
									"value": "中关村"
								},
								{
									"key": "receiverZip",
									"value": "100000"
								}
							]
						}
					},
					"response": []
				},
				{
					"name": "del.do",
					"request": {
						"method": "GET",
						"header": [],
						"body": {
							"mode": "raw",
							"raw": ""
						},
						"url": {
							"raw": "http://localhost:8083/shipping/del.do?shippingId=30",
							"protocol": "http",
							"host": [
								"localhost"
							],
							"port": "8083",
							"path": [
								"shipping",
								"del.do"
							],
							"query": [
								{
									"key": "shippingId",
									"value": "30"
								}
							]
						}
					},
					"response": []
				},
				{
					"name": "update.do",
					"request": {
						"method": "GET",
						"header": [],
						"body": {
							"mode": "raw",
							"raw": ""
						},
						"url": {
							"raw": "http://localhost:8083/shipping/update.do?id=29&receiverName=黄鹤翔&receiverPhone=010&receiverMobile=18688888888&receiverProvince=北京&receiverCity=北京市&receiverAddress=中关村&receiverZip=100000",
							"protocol": "http",
							"host": [
								"localhost"
							],
							"port": "8083",
							"path": [
								"shipping",
								"update.do"
							],
							"query": [
								{
									"key": "id",
									"value": "29"
								},
								{
									"key": "receiverName",
									"value": "黄鹤翔"
								},
								{
									"key": "receiverPhone",
									"value": "010"
								},
								{
									"key": "receiverMobile",
									"value": "18688888888"
								},
								{
									"key": "receiverProvince",
									"value": "北京"
								},
								{
									"key": "receiverCity",
									"value": "北京市"
								},
								{
									"key": "receiverAddress",
									"value": "中关村"
								},
								{
									"key": "receiverZip",
									"value": "100000"
								}
							]
						}
					},
					"response": []
				},
				{
					"name": "select.do",
					"request": {
						"method": "GET",
						"header": [],
						"body": {
							"mode": "raw",
							"raw": ""
						},
						"url": {
							"raw": "http://localhost:8083/shipping/select.do?shippingId=29",
							"protocol": "http",
							"host": [
								"localhost"
							],
							"port": "8083",
							"path": [
								"shipping",
								"select.do"
							],
							"query": [
								{
									"key": "shippingId",
									"value": "29"
								}
							]
						}
					},
					"response": []
				},
				{
					"name": "list.do",
					"request": {
						"method": "GET",
						"header": [],
						"body": {
							"mode": "raw",
							"raw": ""
						},
						"url": {
							"raw": "http://localhost:8083/shipping/list.do",
							"protocol": "http",
							"host": [
								"localhost"
							],
							"port": "8083",
							"path": [
								"shipping",
								"list.do"
							]
						}
					},
					"response": []
				}
			]
		}
	]
}